crc_tool/__init__.py
crc_tool/main.py
crc_tool/input_file_handlers/__init__.py
crc_tool/input_file_handlers/elf_handler.py
crc_tool/input_file_handlers/txt_handler.py
crc_tool/util/__init__.py
crc_tool/util/consts.py
crc_tool/util/util.py
tests/__init__.py
tests/conftest.py
tests/generate_user_record/__init__.py
tests/generate_user_record/conftest.py
tests/generate_user_record/util/__init__.py
tests/generate_user_record/util/consts.py
tests/patch_image/__init__.py
tests/patch_image/integration/__init__.py
tests/patch_image/integration/test_whole_insertion.py
ti_simplelink_crc_tool-1.2.5.0.data/data/version_number.txt
ti_simplelink_crc_tool-1.2.5.0.dist-info/LICENSE.txt
ti_simplelink_crc_tool-1.2.5.0.dist-info/METADATA
ti_simplelink_crc_tool-1.2.5.0.dist-info/WHEEL
ti_simplelink_crc_tool-1.2.5.0.dist-info/entry_points.txt
ti_simplelink_crc_tool-1.2.5.0.dist-info/top_level.txt
ti_simplelink_crc_tool-1.2.5.0.dist-info/RECORD
