Metadata-Version: 2.1
Name: ti-simplelink-crc-tool
Version: 1.2.5.0
Summary: Tool to insert CRCs into ELF files or generate user records for CC23xx and CC27xx devices
Home-page: UNKNOWN
Author: Texas Instruments
Author-email: l-morstad@ti.com
License: UNKNOWN
Platform: UNKNOWN
Requires-Dist: cffi==1.15.1
Requires-Dist: lief==0.12.3
Requires-Dist: mypy
Requires-Dist: pyinstaller==5.6.2
Requires-Dist: pylint
Requires-Dist: pytest
Requires-Dist: pywin32-ctypes
